<?xml version='1.0' encoding='utf-8'?>
<PORT_DATA>
  <rowartic>
    <dir>20100208</dir>
    <file>20100208121614</file>
    <area>1</area>
    <ord>1</ord>
    <pub>1</pub>
  </rowartic>
  <rowartic>
    <dir>20100215</dir>
    <file>20100215112236</file>
    <area>1</area>
    <ord>2</ord>
    <pub>1</pub>
  </rowartic>
  <rowartic>
    <dir>20100208</dir>
    <file>20100208183353</file>
    <area>1</area>
    <ord>3</ord>
    <pub>1</pub>
  </rowartic>
  <rowartic>
    <dir>20100304</dir>
    <file>20100304175942</file>
    <area>1</area>
    <ord>4</ord>
    <pub>1</pub>
  </rowartic>
  <rowartic>
    <dir>20100304</dir>
    <file>20100304181625</file>
    <area>1</area>
    <ord>5</ord>
    <pub>1</pub>
  </rowartic>
  <rowartic>
    <dir>20100215</dir>
    <file>20100215113555</file>
    <area>1</area>
    <ord>6</ord>
    <pub>1</pub>
  </rowartic>
  <rowartic>
    <dir>20100215</dir>
    <file>20100215114831</file>
    <area>1</area>
    <ord>7</ord>
    <pub>1</pub>
  </rowartic>
  <rowartic>
    <dir>20100215</dir>
    <file>20100215150758</file>
    <area>1</area>
    <ord>8</ord>
    <pub>1</pub>
  </rowartic>
</PORT_DATA>